enode/__init__.py
enode/_version.py
enode/basesdk.py
enode/batteries.py
enode/chargers.py
enode/experimental.py
enode/hem_systems.py
enode/hems.py
enode/httpclient.py
enode/hvac.py
enode/hvacs.py
enode/interventions.py
enode/locations.py
enode/meters.py
enode/py.typed
enode/schedules.py
enode/sdk.py
enode/sdkconfiguration.py
enode/servicehealth.py
enode/solar_inverters.py
enode/statistics.py
enode/tariffs.py
enode/user_management.py
enode/vehicles.py
enode/webhooks.py
enode/_hooks/__init__.py
enode/_hooks/clientcredentials.py
enode/_hooks/registration.py
enode/_hooks/sdkhooks.py
enode/_hooks/types.py
enode/errors/__init__.py
enode/errors/cancelbatteryactionop.py
enode/errors/chargeaction_error.py
enode/errors/chargeraction.py
enode/errors/connectionslimitreachedproblem_error.py
enode/errors/enodedefaulterror.py
enode/errors/enodeerror.py
enode/errors/getinverterstatisticsop.py
enode/errors/hvacaction.py
enode/errors/hvacactionfollowschedule_error.py
enode/errors/hvacactionpermanenthold_error.py
enode/errors/maxcurrentaction_error.py
enode/errors/no_response_error.py
enode/errors/problem_error.py
enode/errors/responsevalidationerror.py
enode/errors/updatevehiclesmartchargingpolicyop.py
enode/errors/webhooknotfoundproblem_error.py
enode/errors/webhooknotvalidproblem_error.py
enode/models/__init__.py
enode/models/actionstate.py
enode/models/aggregates.py
enode/models/associateuserlocationwithtariffop.py
enode/models/autopermanenthold.py
enode/models/autotargetstate.py
enode/models/batteriesrefreshhintop.py
enode/models/battery.py
enode/models/batterycapabilities.py
enode/models/batterychargestate.py
enode/models/batteryconfig.py
enode/models/batteryhealth.py
enode/models/batteryinformation.py
enode/models/batterylocation.py
enode/models/batteryvendor.py
enode/models/cancelbatteryactionop.py
enode/models/cancelchargeractionop.py
enode/models/cancelhvacactionop.py
enode/models/cancelvehicleactionop.py
enode/models/capability.py
enode/models/chargeablevendor.py
enode-0.2.6.dist-info/METADATA
enode-0.2.6.dist-info/WHEEL
enode-0.2.6.dist-info/top_level.txt
enode-0.2.6.dist-info/RECORD
